AUTHORS
CHANGELOG.txt
DESCRIPTION
LICENSE
MANIFEST.in
README.md
setup.py
django_registration_email.egg-info/PKG-INFO
django_registration_email.egg-info/SOURCES.txt
django_registration_email.egg-info/dependency_links.txt
django_registration_email.egg-info/top_level.txt
registration_email/__init__.py
registration_email/auth.py
registration_email/auth_urls.py
registration_email/forms.py
registration_email/models.py
registration_email/views.py
registration_email/backends/__init__.py
registration_email/backends/default/__init__.py
registration_email/backends/default/urls.py
registration_email/backends/simple/__init__.py
registration_email/backends/simple/urls.py
registration_email/locale/nl/LC_MESSAGES/django.mo
registration_email/locale/nl/LC_MESSAGES/django.po
registration_email/locale/pl/LC_MESSAGES/django.mo
registration_email/locale/pl/LC_MESSAGES/django.po
registration_email/static/registration_email/css/auth.css
registration_email/templates/registration/activate.html
registration_email/templates/registration/activation_complete.html
registration_email/templates/registration/activation_email.txt
registration_email/templates/registration/activation_email_subject.txt
registration_email/templates/registration/login.html
registration_email/templates/registration/logout.html
registration_email/templates/registration/password_change_done.html
registration_email/templates/registration/password_change_form.html
registration_email/templates/registration/password_reset_complete.html
registration_email/templates/registration/password_reset_confirm.html
registration_email/templates/registration/password_reset_done.html
registration_email/templates/registration/password_reset_email.html
registration_email/templates/registration/password_reset_form.html
registration_email/templates/registration/registration_base.html
registration_email/templates/registration/registration_closed.html
registration_email/templates/registration/registration_complete.html
registration_email/templates/registration/registration_form.html