Metadata-Version: 1.0
Name: django-registration-email
Version: 0.7.1
Summary: Provides a custom authentication backend so that users can signup to the site
